spectral_datawrappers/__init__.py
spectral_datawrappers/config/settings.toml
spectral_datawrappers/config.py
spectral_datawrappers/credit_scoring/__init__.py
spectral_datawrappers/credit_scoring/credit_scoring_wrapper.py
spectral_datawrappers/data_wrappers_interface.py
spectral_datawrappers-0.2.2.dist-info/METADATA
spectral_datawrappers-0.2.2.dist-info/WHEEL
spectral_datawrappers-0.2.2.dist-info/LICENSE
spectral_datawrappers-0.2.2.dist-info/RECORD
