Metadata-Version: 2.1
Name: spectral-datawrappers
Version: 0.2.2
Summary: Library for retrieving data for participating in Spectral's challenges
Author: Your Name
Author-email: you@example.com
Requires-Python: >=3.9,<4.0
Classifier: Programming Language :: Python :: 3
Classifier: Programming Language :: Python :: 3.9
Classifier: Programming Language :: Python :: 3.10
Classifier: Programming Language :: Python :: 3.11
Requires-Dist: dynaconf (>=3.2.3,<4.0.0)
Requires-Dist: pytest (>=7.4.3,<8.0.0)
Requires-Dist: requests (>=2.31.0,<3.0.0)
Requires-Dist: tqdm (>=4.66.1,<5.0.0)
